brian2wasm/__init__.py
brian2wasm/__main__.py
brian2wasm/_version.py
brian2wasm/device.py
brian2wasm/emsdk_setup.bat
brian2wasm/emsdk_setup.sh
brian2wasm/functions.py
brian2wasm/templates/brian.js
brian2wasm/templates/html_template
brian2wasm/templates/makefile
brian2wasm/templates/objects.cpp
brian2wasm/templates/pre.js
brian2wasm/templates/win_makefile
brian2wasm/templates/worker.js
brian2wasm-0.4.2.dist-info/METADATA
brian2wasm-0.4.2.dist-info/WHEEL
brian2wasm-0.4.2.dist-info/entry_points.txt
brian2wasm-0.4.2.dist-info/top_level.txt
brian2wasm-0.4.2.dist-info/RECORD
