Metadata-Version: 2.4
Name: brian2wasm
Version: 0.4.2
Summary: A WebAssembly backend for the Brian 2 simulator
Project-URL: Homepage, https://github.com/brian-team/brian2wasm
Project-URL: Source, https://github.com/brian-team/brian2wasm
Project-URL: Tracker, https://github.com/brian-team/brian2wasm/issues
Keywords: wasm,brian
Requires-Python: >=3.10
